setup.py
Flask_Validates.egg-info/PKG-INFO
Flask_Validates.egg-info/SOURCES.txt
Flask_Validates.egg-info/dependency_links.txt
Flask_Validates.egg-info/not-zip-safe
Flask_Validates.egg-info/requires.txt
Flask_Validates.egg-info/top_level.txt
flask_validates/__init__.py
flask_validates/validates.py